{
  "summary": {
    "csv": "products\\Production\\launch\\dtb_woocommerce_official_catalog.csv",
    "images_dir": "products\\Production\\launch\\launch_images",
    "apply": false,
    "expected_total": 931,
    "expected_present": 735,
    "expected_missing": 196,
    "renamed": 0,
    "target_exists": 0,
    "no_match": 335,
    "ambiguous_match": 0,
    "renamed_and_copied": 0
  },
  "expected_missing": [
    "columbia_tools_hh19_01.webp",
    "columbia_tools_tools_10ffb_01.webp",
    "columbia_tools_tools_12fbb_01.webp",
    "columbia_tools_tools_12ffb_01.webp",
    "columbia_tools_tools_14ffb_01.webp",
    "columbia_tools_tools_25ah_01.webp",
    "columbia_tools_tools_25ah_02.webp",
    "columbia_tools_tools_25ah_03.webp",
    "columbia_tools_tools_25ah_04.webp",
    "columbia_tools_tools_25sf_01.webp",
    "columbia_tools_tools_25sf_02.webp",
    "columbia_tools_tools_2_5csf_01.webp",
    "columbia_tools_tools_2_5df_01.webp",
    "columbia_tools_tools_35ah_01.webp",
    "columbia_tools_tools_35ah_02.webp",
    "columbia_tools_tools_35ah_03.webp",
    "columbia_tools_tools_35ah_04.webp",
    "columbia_tools_tools_35sf_01.webp",
    "columbia_tools_tools_35sf_02.webp",
    "columbia_tools_tools_3_5csf_01.webp",
    "columbia_tools_tools_3_5df_01.webp",
    "columbia_tools_tools_3csf_01.webp",
    "columbia_tools_tools_3df_01.webp",
    "columbia_tools_tools_3sf_01.webp",
    "columbia_tools_tools_3sf_02.webp",
    "columbia_tools_tools_3wtsf_01.webp",
    "columbia_tools_tools_3wtsf_02.webp",
    "columbia_tools_tools_4df_01.webp",
    "columbia_tools_tools_4sf_01.webp",
    "columbia_tools_tools_4sf_02.webp",
    "columbia_tools_tools_55ffb_01.webp",
    "columbia_tools_tools_7ffb_01.webp",
    "columbia_tools_tools_8ffb_01.webp",
    "columbia_tools_tools_chxl_01.webp",
    "columbia_tools_tools_fmh_01.webp",
    "columbia_tools_tools_fmr3x18mm_01.webp",
    "columbia_tools_tools_fmr9x18mm_01.webp",
    "columbia_tools_tools_hmp_01.webp",
    "columbia_tools_tools_ica21_01.webp",
    "columbia_tools_tools_ica21_02.webp",
    "columbia_tools_tools_ica41_01.webp",
    "columbia_tools_tools_ica41_02.webp",
    "columbia_tools_tools_mh_01.webp",
    "columbia_tools_tools_mh_02.webp",
    "columbia_tools_tools_mh_03.webp",
    "columbia_tools_tools_mh_04.webp",
    "columbia_tools_tools_mhl_01.webp",
    "columbia_tools_tools_mhl_02.webp",
    "columbia_tools_tools_mhl_03.webp",
    "columbia_tools_tools_mhl_04.webp",
    "columbia_tools_tools_mhs_01.webp",
    "columbia_tools_tools_mhs_02.webp",
    "columbia_tools_tools_mhs_03.webp",
    "columbia_tools_tools_mhs_04.webp",
    "columbia_tools_tools_pc1hext_01.webp",
    "columbia_tools_tools_pchxl_01.webp",
    "columbia_tools_tools_pddm_01.webp",
    "columbia_tools_tools_pddm_02.webp",
    "columbia_tools_tools_pmhs_01.webp",
    "columbia_tools_tools_pmhs_02.webp",
    "columbia_tools_tools_pmhs_03.webp",
    "columbia_tools_tools_pmhs_04.webp",
    "columbia_tools_tools_pmhs_05.webp",
    "columbia_tools_tools_rc_01.webp",
    "columbia_tools_tools_rc_02.webp",
    "columbia_tools_tools_rc_03.webp",
    "columbia_tools_tools_tbbf_01.webp",
    "columbia_tools_tools_tbgn_01.webp",
    "columbia_tools_tools_tcs_01.webp",
    "columbia_tools_tools_tcs_02.webp",
    "columbia_tools_tools_tl38_01.webp",
    "columbia_tools_tools_tl38_02.webp",
    "columbia_tools_tools_tsb10_01.webp",
    "columbia_tools_tools_tsb10_02.webp",
    "columbia_tools_tools_tsb12_01.webp",
    "columbia_tools_tools_tsb12_02.webp",
    "columbia_tools_tools_tsb14_01.webp",
    "columbia_tools_tools_tsb14_02.webp",
    "columbia_tools_tools_tsb18_01.webp",
    "columbia_tools_tools_tsb18_02.webp",
    "columbia_tools_tools_tsb24_01.webp",
    "columbia_tools_tools_tsb24_02.webp",
    "columbia_tools_tools_tsb32_01.webp",
    "columbia_tools_tools_tsb32_02.webp",
    "columbia_tools_tools_tsb40_01.webp",
    "columbia_tools_tools_tsb40_02.webp",
    "columbia_tools_tools_tsb48_01.webp",
    "columbia_tools_tools_tsb48_02.webp",
    "columbia_tools_tools_tsb7_01.webp",
    "columbia_tools_tools_tsb7_02.webp",
    "dura_stilts_d_iii_01.webp",
    "dura_stilts_d_iii_02.webp",
    "dura_stilts_d_iii_03.webp",
    "level5_4_600p_4_707_02.webp",
    "level5_4_602_01.webp",
    "level5_4_605_01.webp",
    "level5_4_629_01.webp",
    "level5_4_630_4_707_02.webp",
    "level5_4_661p_4_707_02.webp",
    "level5_4_677p_4_707_02.webp",
    "level5_4_687p_4_707_02.webp",
    "level5_4_701_01.webp",
    "level5_4_701_02.webp",
    "level5_4_701_03.webp",
    "level5_4_702_01.webp",
    "level5_4_702_02.webp",
    "level5_4_702_03.webp",
    "level5_4_707_01.webp",
    "level5_4_711_01.webp",
    "level5_4_712_01.webp",
    "level5_4_714_01.webp",
    "level5_4_714_02.webp",
    "level5_4_715_01.webp",
    "level5_4_732_01.webp",
    "level5_4_732_02.webp",
    "level5_4_732_03.webp",
    "level5_4_733_01.webp",
    "level5_4_733_02.webp",
    "level5_4_733_03.webp",
    "level5_4_734_01.webp",
    "level5_4_734_02.webp",
    "level5_4_734_03.webp",
    "level5_4_735_01.webp",
    "level5_4_735_02.webp",
    "level5_4_735_03.webp",
    "level5_4_740_01.webp",
    "level5_4_754_01.webp",
    "level5_4_754_02.webp",
    "level5_4_754_03.webp",
    "level5_4_755_01.webp",
    "level5_4_755_03.webp",
    "level5_4_759_01.webp",
    "level5_4_760_01.webp",
    "level5_4_760_02.webp",
    "level5_4_760_03.webp",
    "level5_4_760_04.webp",
    "level5_4_760_05.webp",
    "level5_4_760_06.webp",
    "level5_4_760_07.webp",
    "level5_4_760_08.webp",
    "level5_4_760_09.webp",
    "level5_4_764_01.webp",
    "level5_4_764_02.webp",
    "level5_4_764_03.webp",
    "level5_4_765_01.webp",
    "level5_4_766_01.webp",
    "level5_4_767_01.webp",
    "level5_4_767_02.webp",
    "level5_4_767_03.webp",
    "level5_4_768_01.webp",
    "level5_4_768_02.webp",
    "level5_4_768_03.webp",
    "level5_4_769_01.webp",
    "level5_4_769_02.webp",
    "level5_4_769_03.webp",
    "level5_4_770_01.webp",
    "level5_4_770_02.webp",
    "level5_4_770_03.webp",
    "level5_4_771_01.webp",
    "level5_4_771_02.webp",
    "level5_4_771_03.webp",
    "level5_4_771_04.webp",
    "level5_4_777_01.webp",
    "level5_4_778_01.webp",
    "level5_4_779_01.webp",
    "level5_4_780_01.webp",
    "level5_4_781_01.webp",
    "level5_4_782_01.webp",
    "level5_4_792_01.webp",
    "level5_4_794_01.webp",
    "level5_4_795_01.webp",
    "level5_4_798_01.webp",
    "level5_4_799_01.webp",
    "level5_4_862_01.webp",
    "level5_5_623_01.webp",
    "surpro_s1_a_1624_01.webp",
    "surpro_s1_a_2030_01.webp",
    "surpro_s1_a_2640_01.webp",
    "surpro_s1_m_1624_01.webp",
    "surpro_s1_m_2030_01.webp",
    "surpro_s1_m_2640_01.webp",
    "surpro_s1x_a_2131_01.webp",
    "surpro_s1x_a_2640_01.webp",
    "surpro_s1x_m_2131_01.webp",
    "surpro_s1x_m_2640_01.webp",
    "surpro_s2_a_1624_01.webp",
    "surpro_s2_a_2030_01.webp",
    "surpro_s2_a_2640_01.webp",
    "surpro_s2_m_1624_01.webp",
    "surpro_s2_m_2030_01.webp",
    "surpro_s2_m_2640_01.webp",
    "surpro_s2x_a_2131_01.webp",
    "surpro_s2x_a_2640_01.webp",
    "surpro_s2x_m_2131_01.webp",
    "surpro_s2x_m_2640_01.webp",
    "tapetech_8034tt_01.webp"
  ],
  "records": [
    {
      "source": "columbia_tools_10ffb_01.webp",
      "target": "columbia_tools_tools_10ffb_01.webp",
      "status": "planned",
      "reason": "matched"
    },
    {
      "source": "columbia_tools_12fbb_01.webp",
      "target": "columbia_tools_tools_12fbb_01.webp",
      "status": "planned",
      "reason": "matched"
    },
    {
      "source": "columbia_tools_12ffb_01.webp",
      "target": "columbia_tools_tools_12ffb_01.webp",
      "status": "planned",
      "reason": "matched"
    },
    {
      "source": "columbia_tools_14ffb_01.webp",
      "target": "columbia_tools_tools_14ffb_01.webp",
      "status": "planned",
      "reason": "matched"
    },
    {
      "source": "columbia_tools_25ah_01.webp",
      "target": "columbia_tools_tools_25ah_01.webp",
      "status": "planned",
      "reason": "matched"
    },
    {
      "source": "columbia_tools_25ah_02.webp",
      "target": "columbia_tools_tools_25ah_02.webp",
      "status": "planned",
      "reason": "matched"
    },
    {
      "source": "columbia_tools_25ah_03.webp",
      "target": "columbia_tools_tools_25ah_03.webp",
      "status": "planned",
      "reason": "matched"
    },
    {
      "source": "columbia_tools_25ah_04.webp",
      "target": "columbia_tools_tools_25ah_04.webp",
      "status": "planned",
      "reason": "matched"
    },
    {
      "source": "columbia_tools_25sf_01.webp",
      "target": "columbia_tools_tools_25sf_01.webp",
      "status": "planned",
      "reason": "matched"
    },
    {
      "source": "columbia_tools_25sf_02.webp",
      "target": "columbia_tools_tools_25sf_02.webp",
      "status": "planned",
      "reason": "matched"
    },
    {
      "source": "columbia_tools_2_5csf_01.webp",
      "target": "columbia_tools_tools_2_5csf_01.webp",
      "status": "planned",
      "reason": "matched"
    },
    {
      "source": "columbia_tools_2_5df_01.webp",
      "target": "columbia_tools_tools_2_5df_01.webp",
      "status": "planned",
      "reason": "matched"
    },
    {
      "source": "columbia_tools_2ah_02.webp",
      "target": "",
      "status": "no_match",
      "reason": "no_match"
    },
    {
      "source": "columbia_tools_2ah_03.webp",
      "target": "",
      "status": "no_match",
      "reason": "no_match"
    },
    {
      "source": "columbia_tools_2ah_04.webp",
      "target": "",
      "status": "no_match",
      "reason": "no_match"
    },
    {
      "source": "columbia_tools_35ah_01.webp",
      "target": "columbia_tools_tools_35ah_01.webp",
      "status": "planned",
      "reason": "matched"
    },
    {
      "source": "columbia_tools_35ah_02.webp",
      "target": "columbia_tools_tools_35ah_02.webp",
      "status": "planned",
      "reason": "matched"
    },
    {
      "source": "columbia_tools_35ah_03.webp",
      "target": "columbia_tools_tools_35ah_03.webp",
      "status": "planned",
      "reason": "matched"
    },
    {
      "source": "columbia_tools_35ah_04.webp",
      "target": "columbia_tools_tools_35ah_04.webp",
      "status": "planned",
      "reason": "matched"
    },
    {
      "source": "columbia_tools_35sf_01.webp",
      "target": "columbia_tools_tools_35sf_01.webp",
      "status": "planned",
      "reason": "matched"
    },
    {
      "source": "columbia_tools_35sf_02.webp",
      "target": "columbia_tools_tools_35sf_02.webp",
      "status": "planned",
      "reason": "matched"
    },
    {
      "source": "columbia_tools_3_5csf_01.webp",
      "target": "columbia_tools_tools_3_5csf_01.webp",
      "status": "planned",
      "reason": "matched"
    },
    {
      "source": "columbia_tools_3_5df_01.webp",
      "target": "columbia_tools_tools_3_5df_01.webp",
      "status": "planned",
      "reason": "matched"
    },
    {
      "source": "columbia_tools_3ah_02.webp",
      "target": "",
      "status": "no_match",
      "reason": "no_match"
    },
    {
      "source": "columbia_tools_3ah_03.webp",
      "target": "",
      "status": "no_match",
      "reason": "no_match"
    },
    {
      "source": "columbia_tools_3ah_04.webp",
      "target": "",
      "status": "no_match",
      "reason": "no_match"
    },
    {
      "source": "columbia_tools_3csf_01.webp",
      "target": "columbia_tools_tools_3csf_01.webp",
      "status": "planned",
      "reason": "matched"
    },
    {
      "source": "columbia_tools_3df_01.webp",
      "target": "columbia_tools_tools_3df_01.webp",
      "status": "planned",
      "reason": "matched"
    },
    {
      "source": "columbia_tools_3sf_01.webp",
      "target": "columbia_tools_tools_3sf_01.webp",
      "status": "planned",
      "reason": "matched"
    },
    {
      "source": "columbia_tools_3sf_02.webp",
      "target": "columbia_tools_tools_3sf_02.webp",
      "status": "planned",
      "reason": "matched"
    },
    {
      "source": "columbia_tools_3wtsf_01.webp",
      "target": "columbia_tools_tools_3wtsf_01.webp",
      "status": "planned",
      "reason": "matched"
    },
    {
      "source": "columbia_tools_3wtsf_02.webp",
      "target": "columbia_tools_tools_3wtsf_02.webp",
      "status": "planned",
      "reason": "matched"
    },
    {
      "source": "columbia_tools_4df_01.webp",
      "target": "columbia_tools_tools_4df_01.webp",
      "status": "planned",
      "reason": "matched"
    },
    {
      "source": "columbia_tools_4sf_01.webp",
      "target": "columbia_tools_tools_4sf_01.webp",
      "status": "planned",
      "reason": "matched"
    },
    {
      "source": "columbia_tools_4sf_02.webp",
      "target": "columbia_tools_tools_4sf_02.webp",
      "status": "planned",
      "reason": "matched"
    },
    {
      "source": "columbia_tools_55ffb_01.webp",
      "target": "columbia_tools_tools_55ffb_01.webp",
      "status": "planned",
      "reason": "matched"
    },
    {
      "source": "columbia_tools_7cfb_02.webp",
      "target": "",
      "status": "no_match",
      "reason": "no_match"
    },
    {
      "source": "columbia_tools_7cfb_03.webp",
      "target": "",
      "status": "no_match",
      "reason": "no_match"
    },
    {
      "source": "columbia_tools_7cfb_04.webp",
      "target": "",
      "status": "no_match",
      "reason": "no_match"
    },
    {
      "source": "columbia_tools_7ffb_01.webp",
      "target": "columbia_tools_tools_7ffb_01.webp",
      "status": "planned",
      "reason": "matched"
    },
    {
      "source": "columbia_tools_8cfb_02.webp",
      "target": "",
      "status": "no_match",
      "reason": "no_match"
    },
    {
      "source": "columbia_tools_8cfb_03.webp",
      "target": "",
      "status": "no_match",
      "reason": "no_match"
    },
    {
      "source": "columbia_tools_8cfb_04.webp",
      "target": "",
      "status": "no_match",
      "reason": "no_match"
    },
    {
      "source": "columbia_tools_8ffb_01.webp",
      "target": "columbia_tools_tools_8ffb_01.webp",
      "status": "planned",
      "reason": "matched"
    },
    {
      "source": "columbia_tools_c1h_02.webp",
      "target": "",
      "status": "no_match",
      "reason": "no_match"
    },
    {
      "source": "columbia_tools_c1h_03.webp",
      "target": "",
      "status": "no_match",
      "reason": "no_match"
    },
    {
      "source": "columbia_tools_c1hext_02.webp",
      "target": "",
      "status": "no_match",
      "reason": "no_match"
    },
    {
      "source": "columbia_tools_c1hext_03.webp",
      "target": "",
      "status": "no_match",
      "reason": "no_match"
    },
    {
      "source": "columbia_tools_c1hs_01.webp",
      "target": "",
      "status": "no_match",
      "reason": "no_match"
    },
    {
      "source": "columbia_tools_c1hs_02.webp",
      "target": "",
      "status": "no_match",
      "reason": "no_match"
    },
    {
      "source": "columbia_tools_c1hs_03.webp",
      "target": "",
      "status": "no_match",
      "reason": "no_match"
    },
    {
      "source": "columbia_tools_cbncr_02.webp",
      "target": "",
      "status": "no_match",
      "reason": "no_match"
    },
    {
      "source": "columbia_tools_cbncr_03.webp",
      "target": "",
      "status": "no_match",
      "reason": "no_match"
    },
    {
      "source": "columbia_tools_cext90_02.webp",
      "target": "",
      "status": "no_match",
      "reason": "no_match"
    },
    {
      "source": "columbia_tools_chxl_01.webp",
      "target": "columbia_tools_tools_chxl_01.webp",
      "status": "planned",
      "reason": "matched"
    },
    {
      "source": "columbia_tools_clt32_01.webp",
      "target": "",
      "status": "no_match",
      "reason": "no_match"
    },
    {
      "source": "columbia_tools_clt42_01.webp",
      "target": "",
      "status": "no_match",
      "reason": "no_match"
    },
    {
      "source": "columbia_tools_clt55_01.webp",
      "target": "",
      "status": "no_match",
      "reason": "no_match"
    },
    {
      "source": "columbia_tools_cmt32_01.webp",
      "target": "",
      "status": "no_match",
      "reason": "no_match"
    },
    {
      "source": "columbia_tools_cmt42_01.webp",
      "target": "",
      "status": "no_match",
      "reason": "no_match"
    },
    {
      "source": "columbia_tools_cmt55_01.webp",
      "target": "",
      "status": "no_match",
      "reason": "no_match"
    },
    {
      "source": "columbia_tools_cobcr_02.webp",
      "target": "",
      "status": "no_match",
      "reason": "no_match"
    },
    {
      "source": "columbia_tools_cobcr_03.webp",
      "target": "",
      "status": "no_match",
      "reason": "no_match"
    },
    {
      "source": "columbia_tools_cobcre_02.webp",
      "target": "",
      "status": "no_match",
      "reason": "no_match"
    },
    {
      "source": "columbia_tools_cobcre_03.webp",
      "target": "",
      "status": "no_match",
      "reason": "no_match"
    },
    {
      "source": "columbia_tools_cobcrw_02.webp",
      "target": "",
      "status": "no_match",
      "reason": "no_match"
    },
    {
      "source": "columbia_tools_cobcrw_03.webp",
      "target": "",
      "status": "no_match",
      "reason": "no_match"
    },
    {
      "source": "columbia_tools_col_mud_roller_replacement_01.webp",
      "target": "",
      "status": "no_match",
      "reason": "no_match"
    },
    {
      "source": "columbia_tools_cs_01.webp",
      "target": "",
      "status": "no_match",
      "reason": "no_match"
    },
    {
      "source": "columbia_tools_csh_01.webp",
      "target": "",
      "status": "no_match",
      "reason": "no_match"
    },
    {
      "source": "columbia_tools_fmr3x18mm_01.webp",
      "target": "columbia_tools_tools_fmr3x18mm_01.webp",
      "status": "planned",
      "reason": "matched"
    },
    {
      "source": "columbia_tools_fmr9x18mm_01.webp",
      "target": "columbia_tools_tools_fmr9x18mm_01.webp",
      "status": "planned",
      "reason": "matched"
    },
    {
      "source": "columbia_tools_ica21_01.webp",
      "target": "columbia_tools_tools_ica21_01.webp",
      "status": "planned",
      "reason": "matched"
    },
    {
      "source": "columbia_tools_ica21_02.webp",
      "target": "columbia_tools_tools_ica21_02.webp",
      "status": "planned",
      "reason": "matched"
    },
    {
      "source": "columbia_tools_ica41_01.webp",
      "target": "columbia_tools_tools_ica41_01.webp",
      "status": "planned",
      "reason": "matched"
    },
    {
      "source": "columbia_tools_ica41_02.webp",
      "target": "columbia_tools_tools_ica41_02.webp",
      "status": "planned",
      "reason": "matched"
    },
    {
      "source": "columbia_tools_mh_01.webp",
      "target": "columbia_tools_tools_mh_01.webp",
      "status": "planned",
      "reason": "matched"
    },
    {
      "source": "columbia_tools_mh_02.webp",
      "target": "columbia_tools_tools_mh_02.webp",
      "status": "planned",
      "reason": "matched"
    },
    {
      "source": "columbia_tools_mh_03.webp",
      "target": "columbia_tools_tools_mh_03.webp",
      "status": "planned",
      "reason": "matched"
    },
    {
      "source": "columbia_tools_mh_04.webp",
      "target": "columbia_tools_tools_mh_04.webp",
      "status": "planned",
      "reason": "matched"
    },
    {
      "source": "columbia_tools_mhl_01.webp",
      "target": "columbia_tools_tools_mhl_01.webp",
      "status": "planned",
      "reason": "matched"
    },
    {
      "source": "columbia_tools_mhl_02.webp",
      "target": "columbia_tools_tools_mhl_02.webp",
      "status": "planned",
      "reason": "matched"
    },
    {
      "source": "columbia_tools_mhl_03.webp",
      "target": "columbia_tools_tools_mhl_03.webp",
      "status": "planned",
      "reason": "matched"
    },
    {
      "source": "columbia_tools_mhl_04.webp",
      "target": "columbia_tools_tools_mhl_04.webp",
      "status": "planned",
      "reason": "matched"
    },
    {
      "source": "columbia_tools_mhs_01.webp",
      "target": "columbia_tools_tools_mhs_01.webp",
      "status": "planned",
      "reason": "matched"
    },
    {
      "source": "columbia_tools_mhs_02.webp",
      "target": "columbia_tools_tools_mhs_02.webp",
      "status": "planned",
      "reason": "matched"
    },
    {
      "source": "columbia_tools_mhs_03.webp",
      "target": "columbia_tools_tools_mhs_03.webp",
      "status": "planned",
      "reason": "matched"
    },
    {
      "source": "columbia_tools_mhs_04.webp",
      "target": "columbia_tools_tools_mhs_04.webp",
      "status": "planned",
      "reason": "matched"
    },
    {
      "source": "columbia_tools_pc1hext_01.webp",
      "target": "columbia_tools_tools_pc1hext_01.webp",
      "status": "planned",
      "reason": "matched"
    },
    {
      "source": "columbia_tools_pchxl_01.webp",
      "target": "columbia_tools_tools_pchxl_01.webp",
      "status": "planned",
      "reason": "matched"
    },
    {
      "source": "columbia_tools_pcmt42_01.webp",
      "target": "",
      "status": "no_match",
      "reason": "no_match"
    },
    {
      "source": "columbia_tools_pcmt42_02.webp",
      "target": "",
      "status": "no_match",
      "reason": "no_match"
    },
    {
      "source": "columbia_tools_pcmt42_03.webp",
      "target": "",
      "status": "no_match",
      "reason": "no_match"
    },
    {
      "source": "columbia_tools_pcmt42_04.webp",
      "target": "",
      "status": "no_match",
      "reason": "no_match"
    },
    {
      "source": "columbia_tools_pcmt42_05.webp",
      "target": "",
      "status": "no_match",
      "reason": "no_match"
    },
    {
      "source": "columbia_tools_pcmt42_06.webp",
      "target": "",
      "status": "no_match",
      "reason": "no_match"
    },
    {
      "source": "columbia_tools_pcmt42_07.webp",
      "target": "",
      "status": "no_match",
      "reason": "no_match"
    },
    {
      "source": "columbia_tools_pddm_01.webp",
      "target": "columbia_tools_tools_pddm_01.webp",
      "status": "planned",
      "reason": "matched"
    },
    {
      "source": "columbia_tools_pddm_02.webp",
      "target": "columbia_tools_tools_pddm_02.webp",
      "status": "planned",
      "reason": "matched"
    },
    {
      "source": "columbia_tools_pmhs_01.webp",
      "target": "columbia_tools_tools_pmhs_01.webp",
      "status": "planned",
      "reason": "matched"
    },
    {
      "source": "columbia_tools_pmhs_02.webp",
      "target": "columbia_tools_tools_pmhs_02.webp",
      "status": "planned",
      "reason": "matched"
    },
    {
      "source": "columbia_tools_pmhs_03.webp",
      "target": "columbia_tools_tools_pmhs_03.webp",
      "status": "planned",
      "reason": "matched"
    },
    {
      "source": "columbia_tools_pmhs_04.webp",
      "target": "columbia_tools_tools_pmhs_04.webp",
      "status": "planned",
      "reason": "matched"
    },
    {
      "source": "columbia_tools_pmhs_05.webp",
      "target": "columbia_tools_tools_pmhs_05.webp",
      "status": "planned",
      "reason": "matched"
    },
    {
      "source": "columbia_tools_ptaper_02.webp",
      "target": "",
      "status": "no_match",
      "reason": "no_match"
    },
    {
      "source": "columbia_tools_rc_01.webp",
      "target": "columbia_tools_tools_rc_01.webp",
      "status": "planned",
      "reason": "matched"
    },
    {
      "source": "columbia_tools_rc_02.webp",
      "target": "columbia_tools_tools_rc_02.webp",
      "status": "planned",
      "reason": "matched"
    },
    {
      "source": "columbia_tools_rc_03.webp",
      "target": "columbia_tools_tools_rc_03.webp",
      "status": "planned",
      "reason": "matched"
    },
    {
      "source": "columbia_tools_sacs_02.webp",
      "target": "",
      "status": "no_match",
      "reason": "no_match"
    },
    {
      "source": "columbia_tools_staper_01.webp",
      "target": "",
      "status": "no_match",
      "reason": "no_match"
    },
    {
      "source": "columbia_tools_tbbf_01.webp",
      "target": "columbia_tools_tools_tbbf_01.webp",
      "status": "planned",
      "reason": "matched"
    },
    {
      "source": "columbia_tools_tbgn_01.webp",
      "target": "columbia_tools_tools_tbgn_01.webp",
      "status": "planned",
      "reason": "matched"
    },
    {
      "source": "columbia_tools_tcs_01.webp",
      "target": "columbia_tools_tools_tcs_01.webp",
      "status": "planned",
      "reason": "matched"
    },
    {
      "source": "columbia_tools_tcs_02.webp",
      "target": "columbia_tools_tools_tcs_02.webp",
      "status": "planned",
      "reason": "matched"
    },
    {
      "source": "columbia_tools_tl38_01.webp",
      "target": "columbia_tools_tools_tl38_01.webp",
      "status": "planned",
      "reason": "matched"
    },
    {
      "source": "columbia_tools_tl38_02.webp",
      "target": "columbia_tools_tools_tl38_02.webp",
      "status": "planned",
      "reason": "matched"
    },
    {
      "source": "columbia_tools_tsb10_01.webp",
      "target": "columbia_tools_tools_tsb10_01.webp",
      "status": "planned",
      "reason": "matched"
    },
    {
      "source": "columbia_tools_tsb10_02.webp",
      "target": "columbia_tools_tools_tsb10_02.webp",
      "status": "planned",
      "reason": "matched"
    },
    {
      "source": "columbia_tools_tsb12_01.webp",
      "target": "columbia_tools_tools_tsb12_01.webp",
      "status": "planned",
      "reason": "matched"
    },
    {
      "source": "columbia_tools_tsb12_02.webp",
      "target": "columbia_tools_tools_tsb12_02.webp",
      "status": "planned",
      "reason": "matched"
    },
    {
      "source": "columbia_tools_tsb14_01.webp",
      "target": "columbia_tools_tools_tsb14_01.webp",
      "status": "planned",
      "reason": "matched"
    },
    {
      "source": "columbia_tools_tsb14_02.webp",
      "target": "columbia_tools_tools_tsb14_02.webp",
      "status": "planned",
      "reason": "matched"
    },
    {
      "source": "columbia_tools_tsb18_01.webp",
      "target": "columbia_tools_tools_tsb18_01.webp",
      "status": "planned",
      "reason": "matched"
    },
    {
      "source": "columbia_tools_tsb18_02.webp",
      "target": "columbia_tools_tools_tsb18_02.webp",
      "status": "planned",
      "reason": "matched"
    },
    {
      "source": "columbia_tools_tsb24_01.webp",
      "target": "columbia_tools_tools_tsb24_01.webp",
      "status": "planned",
      "reason": "matched"
    },
    {
      "source": "columbia_tools_tsb24_02.webp",
      "target": "columbia_tools_tools_tsb24_02.webp",
      "status": "planned",
      "reason": "matched"
    },
    {
      "source": "columbia_tools_tsb32_01.webp",
      "target": "columbia_tools_tools_tsb32_01.webp",
      "status": "planned",
      "reason": "matched"
    },
    {
      "source": "columbia_tools_tsb32_02.webp",
      "target": "columbia_tools_tools_tsb32_02.webp",
      "status": "planned",
      "reason": "matched"
    },
    {
      "source": "columbia_tools_tsb40_01.webp",
      "target": "columbia_tools_tools_tsb40_01.webp",
      "status": "planned",
      "reason": "matched"
    },
    {
      "source": "columbia_tools_tsb40_02.webp",
      "target": "columbia_tools_tools_tsb40_02.webp",
      "status": "planned",
      "reason": "matched"
    },
    {
      "source": "columbia_tools_tsb48_01.webp",
      "target": "columbia_tools_tools_tsb48_01.webp",
      "status": "planned",
      "reason": "matched"
    },
    {
      "source": "columbia_tools_tsb48_02.webp",
      "target": "columbia_tools_tools_tsb48_02.webp",
      "status": "planned",
      "reason": "matched"
    },
    {
      "source": "columbia_tools_tsb7_01.webp",
      "target": "columbia_tools_tools_tsb7_01.webp",
      "status": "planned",
      "reason": "matched"
    },
    {
      "source": "columbia_tools_tsb7_02.webp",
      "target": "columbia_tools_tools_tsb7_02.webp",
      "status": "planned",
      "reason": "matched"
    },
    {
      "source": "columbia_tools_tws_02.webp",
      "target": "",
      "status": "no_match",
      "reason": "no_match"
    },
    {
      "source": "tapetech_03tt_03.webp",
      "target": "",
      "status": "no_match",
      "reason": "no_match"
    },
    {
      "source": "tapetech_15tte_04.webp",
      "target": "",
      "status": "no_match",
      "reason": "no_match"
    },
    {
      "source": "tapetech_15tte_05.webp",
      "target": "",
      "status": "no_match",
      "reason": "no_match"
    },
    {
      "source": "tapetech_15tte_06.webp",
      "target": "",
      "status": "no_match",
      "reason": "no_match"
    },
    {
      "source": "tapetech_15tte_07.webp",
      "target": "",
      "status": "no_match",
      "reason": "no_match"
    },
    {
      "source": "tapetech_15tte_08.webp",
      "target": "",
      "status": "no_match",
      "reason": "no_match"
    },
    {
      "source": "tapetech_17tt_03.webp",
      "target": "",
      "status": "no_match",
      "reason": "no_match"
    },
    {
      "source": "tapetech_17tt_04.webp",
      "target": "",
      "status": "no_match",
      "reason": "no_match"
    },
    {
      "source": "tapetech_17tt_05.webp",
      "target": "",
      "status": "no_match",
      "reason": "no_match"
    },
    {
      "source": "tapetech_17tte_03.webp",
      "target": "",
      "status": "no_match",
      "reason": "no_match"
    },
    {
      "source": "tapetech_40xtt_02.webp",
      "target": "",
      "status": "no_match",
      "reason": "no_match"
    },
    {
      "source": "tapetech_40xtt_03.webp",
      "target": "",
      "status": "no_match",
      "reason": "no_match"
    },
    {
      "source": "tapetech_42tt_02.webp",
      "target": "",
      "status": "no_match",
      "reason": "no_match"
    },
    {
      "source": "tapetech_48tt_02.webp",
      "target": "",
      "status": "no_match",
      "reason": "no_match"
    },
    {
      "source": "tapetech_48xtt_02.webp",
      "target": "",
      "status": "no_match",
      "reason": "no_match"
    },
    {
      "source": "tapetech_48xtt_03.webp",
      "target": "",
      "status": "no_match",
      "reason": "no_match"
    },
    {
      "source": "tapetech_48xtt_04.webp",
      "target": "",
      "status": "no_match",
      "reason": "no_match"
    },
    {
      "source": "tapetech_76tt_02.webp",
      "target": "",
      "status": "no_match",
      "reason": "no_match"
    },
    {
      "source": "tapetech_76tt_03.webp",
      "target": "",
      "status": "no_match",
      "reason": "no_match"
    },
    {
      "source": "tapetech_76tt_04.webp",
      "target": "",
      "status": "no_match",
      "reason": "no_match"
    },
    {
      "source": "tapetech_76tt_05.webp",
      "target": "",
      "status": "no_match",
      "reason": "no_match"
    },
    {
      "source": "tapetech_76xltt_02.webp",
      "target": "",
      "status": "no_match",
      "reason": "no_match"
    },
    {
      "source": "tapetech_76xltt_03.webp",
      "target": "",
      "status": "no_match",
      "reason": "no_match"
    },
    {
      "source": "tapetech_76xltt_04.webp",
      "target": "",
      "status": "no_match",
      "reason": "no_match"
    },
    {
      "source": "tapetech_76xltt_05.webp",
      "target": "",
      "status": "no_match",
      "reason": "no_match"
    },
    {
      "source": "tapetech_76xltt_06.webp",
      "target": "",
      "status": "no_match",
      "reason": "no_match"
    },
    {
      "source": "tapetech_8000tt_02.webp",
      "target": "",
      "status": "no_match",
      "reason": "no_match"
    },
    {
      "source": "tapetech_8000tt_03.webp",
      "target": "",
      "status": "no_match",
      "reason": "no_match"
    },
    {
      "source": "tapetech_8000tt_04.webp",
      "target": "",
      "status": "no_match",
      "reason": "no_match"
    },
    {
      "source": "tapetech_8000tt_05.webp",
      "target": "",
      "status": "no_match",
      "reason": "no_match"
    },
    {
      "source": "tapetech_8000tt_06.webp",
      "target": "",
      "status": "no_match",
      "reason": "no_match"
    },
    {
      "source": "tapetech_8000tt_07.webp",
      "target": "",
      "status": "no_match",
      "reason": "no_match"
    },
    {
      "source": "tapetech_8000tt_08.webp",
      "target": "",
      "status": "no_match",
      "reason": "no_match"
    },
    {
      "source": "tapetech_8034tt_02.webp",
      "target": "",
      "status": "no_match",
      "reason": "no_match"
    },
    {
      "source": "tapetech_8034tt_03.webp",
      "target": "",
      "status": "no_match",
      "reason": "no_match"
    },
    {
      "source": "tapetech_8042tt_02.webp",
      "target": "",
      "status": "no_match",
      "reason": "no_match"
    },
    {
      "source": "tapetech_8042tt_03.webp",
      "target": "",
      "status": "no_match",
      "reason": "no_match"
    },
    {
      "source": "tapetech_8042tt_04.webp",
      "target": "",
      "status": "no_match",
      "reason": "no_match"
    },
    {
      "source": "tapetech_8054tt_02.webp",
      "target": "",
      "status": "no_match",
      "reason": "no_match"
    },
    {
      "source": "tapetech_8054tt_03.webp",
      "target": "",
      "status": "no_match",
      "reason": "no_match"
    },
    {
      "source": "tapetech_8072tt_02.webp",
      "target": "",
      "status": "no_match",
      "reason": "no_match"
    },
    {
      "source": "tapetech_8072tt_03.webp",
      "target": "",
      "status": "no_match",
      "reason": "no_match"
    },
    {
      "source": "tapetech_8134tt_02.webp",
      "target": "",
      "status": "no_match",
      "reason": "no_match"
    },
    {
      "source": "tapetech_8134tt_03.webp",
      "target": "",
      "status": "no_match",
      "reason": "no_match"
    },
    {
      "source": "tapetech_8134tt_04.webp",
      "target": "",
      "status": "no_match",
      "reason": "no_match"
    },
    {
      "source": "tapetech_8134tt_05.webp",
      "target": "",
      "status": "no_match",
      "reason": "no_match"
    },
    {
      "source": "tapetech_8134tt_06.webp",
      "target": "",
      "status": "no_match",
      "reason": "no_match"
    },
    {
      "source": "tapetech_8142tt_02.webp",
      "target": "",
      "status": "no_match",
      "reason": "no_match"
    },
    {
      "source": "tapetech_8142tt_03.webp",
      "target": "",
      "status": "no_match",
      "reason": "no_match"
    },
    {
      "source": "tapetech_8154tt_02.webp",
      "target": "",
      "status": "no_match",
      "reason": "no_match"
    },
    {
      "source": "tapetech_8154tt_03.webp",
      "target": "",
      "status": "no_match",
      "reason": "no_match"
    },
    {
      "source": "tapetech_8172tt_02.webp",
      "target": "",
      "status": "no_match",
      "reason": "no_match"
    },
    {
      "source": "tapetech_85t_02.webp",
      "target": "",
      "status": "no_match",
      "reason": "no_match"
    },
    {
      "source": "tapetech_85xltt_03.webp",
      "target": "",
      "status": "no_match",
      "reason": "no_match"
    },
    {
      "source": "tapetech_88tte_05.webp",
      "target": "",
      "status": "no_match",
      "reason": "no_match"
    },
    {
      "source": "tapetech_90t_03.webp",
      "target": "",
      "status": "no_match",
      "reason": "no_match"
    },
    {
      "source": "tapetech_90t_04.webp",
      "target": "",
      "status": "no_match",
      "reason": "no_match"
    },
    {
      "source": "tapetech_atx01tt_04.webp",
      "target": "",
      "status": "no_match",
      "reason": "no_match"
    },
    {
      "source": "tapetech_atx01tt_05.webp",
      "target": "",
      "status": "no_match",
      "reason": "no_match"
    },
    {
      "source": "tapetech_bh_03.webp",
      "target": "",
      "status": "no_match",
      "reason": "no_match"
    },
    {
      "source": "tapetech_bhe_03.webp",
      "target": "",
      "status": "no_match",
      "reason": "no_match"
    },
    {
      "source": "tapetech_ca07tt_02.webp",
      "target": "",
      "status": "no_match",
      "reason": "no_match"
    },
    {
      "source": "tapetech_ca07tt_03.webp",
      "target": "",
      "status": "no_match",
      "reason": "no_match"
    },
    {
      "source": "tapetech_ca07tt_04.webp",
      "target": "",
      "status": "no_match",
      "reason": "no_match"
    },
    {
      "source": "tapetech_ca08tt_02.webp",
      "target": "",
      "status": "no_match",
      "reason": "no_match"
    },
    {
      "source": "tapetech_ca08tt_03.webp",
      "target": "",
      "status": "no_match",
      "reason": "no_match"
    },
    {
      "source": "tapetech_ca08tt_04.webp",
      "target": "",
      "status": "no_match",
      "reason": "no_match"
    },
    {
      "source": "tapetech_ca08tt_05.webp",
      "target": "",
      "status": "no_match",
      "reason": "no_match"
    },
    {
      "source": "tapetech_ca08tt_06.webp",
      "target": "",
      "status": "no_match",
      "reason": "no_match"
    },
    {
      "source": "tapetech_ccage04_01.webp",
      "target": "",
      "status": "no_match",
      "reason": "no_match"
    },
    {
      "source": "tapetech_ccage04_02.webp",
      "target": "",
      "status": "no_match",
      "reason": "no_match"
    },
    {
      "source": "tapetech_ccage04_03.webp",
      "target": "",
      "status": "no_match",
      "reason": "no_match"
    },
    {
      "source": "tapetech_ccage04_04.webp",
      "target": "",
      "status": "no_match",
      "reason": "no_match"
    },
    {
      "source": "tapetech_ccage04_05.webp",
      "target": "",
      "status": "no_match",
      "reason": "no_match"
    },
    {
      "source": "tapetech_ccage04_06.webp",
      "target": "",
      "status": "no_match",
      "reason": "no_match"
    },
    {
      "source": "tapetech_ccage04_07.webp",
      "target": "",
      "status": "no_match",
      "reason": "no_match"
    },
    {
      "source": "tapetech_ccage04_08.webp",
      "target": "",
      "status": "no_match",
      "reason": "no_match"
    },
    {
      "source": "tapetech_ccage04_09.webp",
      "target": "",
      "status": "no_match",
      "reason": "no_match"
    },
    {
      "source": "tapetech_ccage04_10.webp",
      "target": "",
      "status": "no_match",
      "reason": "no_match"
    },
    {
      "source": "tapetech_ccage09_01.webp",
      "target": "",
      "status": "no_match",
      "reason": "no_match"
    },
    {
      "source": "tapetech_ccage09_02.webp",
      "target": "",
      "status": "no_match",
      "reason": "no_match"
    },
    {
      "source": "tapetech_ccage09_03.webp",
      "target": "",
      "status": "no_match",
      "reason": "no_match"
    },
    {
      "source": "tapetech_ccage09_04.webp",
      "target": "",
      "status": "no_match",
      "reason": "no_match"
    },
    {
      "source": "tapetech_ccage09_05.webp",
      "target": "",
      "status": "no_match",
      "reason": "no_match"
    },
    {
      "source": "tapetech_ccage09_06.webp",
      "target": "",
      "status": "no_match",
      "reason": "no_match"
    },
    {
      "source": "tapetech_ccage09_07.webp",
      "target": "",
      "status": "no_match",
      "reason": "no_match"
    },
    {
      "source": "tapetech_ccage09_08.webp",
      "target": "",
      "status": "no_match",
      "reason": "no_match"
    },
    {
      "source": "tapetech_ccage09_09.webp",
      "target": "",
      "status": "no_match",
      "reason": "no_match"
    },
    {
      "source": "tapetech_ccage09_10.webp",
      "target": "",
      "status": "no_match",
      "reason": "no_match"
    },
    {
      "source": "tapetech_ccage12_01.webp",
      "target": "",
      "status": "no_match",
      "reason": "no_match"
    },
    {
      "source": "tapetech_ccage12_02.webp",
      "target": "",
      "status": "no_match",
      "reason": "no_match"
    },
    {
      "source": "tapetech_ccage12_03.webp",
      "target": "",
      "status": "no_match",
      "reason": "no_match"
    },
    {
      "source": "tapetech_ccage12_04.webp",
      "target": "",
      "status": "no_match",
      "reason": "no_match"
    },
    {
      "source": "tapetech_ccage12_05.webp",
      "target": "",
      "status": "no_match",
      "reason": "no_match"
    },
    {
      "source": "tapetech_ccage12_06.webp",
      "target": "",
      "status": "no_match",
      "reason": "no_match"
    },
    {
      "source": "tapetech_ccage12_07.webp",
      "target": "",
      "status": "no_match",
      "reason": "no_match"
    },
    {
      "source": "tapetech_ccage12_08.webp",
      "target": "",
      "status": "no_match",
      "reason": "no_match"
    },
    {
      "source": "tapetech_ccage12_09.webp",
      "target": "",
      "status": "no_match",
      "reason": "no_match"
    },
    {
      "source": "tapetech_ck06cstt_01.webp",
      "target": "",
      "status": "no_match",
      "reason": "no_match"
    },
    {
      "source": "tapetech_ck06cstt_02.webp",
      "target": "",
      "status": "no_match",
      "reason": "no_match"
    },
    {
      "source": "tapetech_ck06cstt_03.webp",
      "target": "",
      "status": "no_match",
      "reason": "no_match"
    },
    {
      "source": "tapetech_ck06cstt_04.webp",
      "target": "",
      "status": "no_match",
      "reason": "no_match"
    },
    {
      "source": "tapetech_ck06cstt_05.webp",
      "target": "",
      "status": "no_match",
      "reason": "no_match"
    },
    {
      "source": "tapetech_crollhan2_05.webp",
      "target": "",
      "status": "no_match",
      "reason": "no_match"
    },
    {
      "source": "tapetech_crollhan2_06.webp",
      "target": "",
      "status": "no_match",
      "reason": "no_match"
    },
    {
      "source": "tapetech_crollhan2_07.webp",
      "target": "",
      "status": "no_match",
      "reason": "no_match"
    },
    {
      "source": "tapetech_eexset590_01.webp",
      "target": "",
      "status": "no_match",
      "reason": "no_match"
    },
    {
      "source": "tapetech_efloat0512n_01.webp",
      "target": "",
      "status": "no_match",
      "reason": "no_match"
    },
    {
      "source": "tapetech_ehc07_02.webp",
      "target": "",
      "status": "no_match",
      "reason": "no_match"
    },
    {
      "source": "tapetech_ehc07_03.webp",
      "target": "",
      "status": "no_match",
      "reason": "no_match"
    },
    {
      "source": "tapetech_ehc10_02.webp",
      "target": "",
      "status": "no_match",
      "reason": "no_match"
    },
    {
      "source": "tapetech_ehc10_03.webp",
      "target": "",
      "status": "no_match",
      "reason": "no_match"
    },
    {
      "source": "tapetech_ehc10_04.webp",
      "target": "",
      "status": "no_match",
      "reason": "no_match"
    },
    {
      "source": "tapetech_ehc12_02.webp",
      "target": "",
      "status": "no_match",
      "reason": "no_match"
    },
    {
      "source": "tapetech_ehc12_03.webp",
      "target": "",
      "status": "no_match",
      "reason": "no_match"
    },
    {
      "source": "tapetech_ehc12_04.webp",
      "target": "",
      "status": "no_match",
      "reason": "no_match"
    },
    {
      "source": "tapetech_ehc12_05.webp",
      "target": "",
      "status": "no_match",
      "reason": "no_match"
    },
    {
      "source": "tapetech_einset590_01.webp",
      "target": "",
      "status": "no_match",
      "reason": "no_match"
    },
    {
      "source": "tapetech_ez07tt_02.webp",
      "target": "",
      "status": "no_match",
      "reason": "no_match"
    },
    {
      "source": "tapetech_ez07tt_03.webp",
      "target": "",
      "status": "no_match",
      "reason": "no_match"
    },
    {
      "source": "tapetech_ez07tt_04.webp",
      "target": "",
      "status": "no_match",
      "reason": "no_match"
    },
    {
      "source": "tapetech_ez07tt_05.webp",
      "target": "",
      "status": "no_match",
      "reason": "no_match"
    },
    {
      "source": "tapetech_ez07tt_06.webp",
      "target": "",
      "status": "no_match",
      "reason": "no_match"
    },
    {
      "source": "tapetech_ez07tt_07.webp",
      "target": "",
      "status": "no_match",
      "reason": "no_match"
    },
    {
      "source": "tapetech_ez07tt_08.webp",
      "target": "",
      "status": "no_match",
      "reason": "no_match"
    },
    {
      "source": "tapetech_ez07tt_09.webp",
      "target": "",
      "status": "no_match",
      "reason": "no_match"
    },
    {
      "source": "tapetech_ez10tt_02.webp",
      "target": "",
      "status": "no_match",
      "reason": "no_match"
    },
    {
      "source": "tapetech_ez10tt_03.webp",
      "target": "",
      "status": "no_match",
      "reason": "no_match"
    },
    {
      "source": "tapetech_ez10tt_04.webp",
      "target": "",
      "status": "no_match",
      "reason": "no_match"
    },
    {
      "source": "tapetech_ez10tt_05.webp",
      "target": "",
      "status": "no_match",
      "reason": "no_match"
    },
    {
      "source": "tapetech_ez10tt_06.webp",
      "target": "",
      "status": "no_match",
      "reason": "no_match"
    },
    {
      "source": "tapetech_ez12tt_02.webp",
      "target": "",
      "status": "no_match",
      "reason": "no_match"
    },
    {
      "source": "tapetech_ez12tt_03.webp",
      "target": "",
      "status": "no_match",
      "reason": "no_match"
    },
    {
      "source": "tapetech_ez12tt_04.webp",
      "target": "",
      "status": "no_match",
      "reason": "no_match"
    },
    {
      "source": "tapetech_ez12tt_05.webp",
      "target": "",
      "status": "no_match",
      "reason": "no_match"
    },
    {
      "source": "tapetech_ez12tt_06.webp",
      "target": "",
      "status": "no_match",
      "reason": "no_match"
    },
    {
      "source": "tapetech_ez12tt_07.webp",
      "target": "",
      "status": "no_match",
      "reason": "no_match"
    },
    {
      "source": "tapetech_ez12tt_08.webp",
      "target": "",
      "status": "no_match",
      "reason": "no_match"
    },
    {
      "source": "tapetech_ez12tt_09.webp",
      "target": "",
      "status": "no_match",
      "reason": "no_match"
    },
    {
      "source": "tapetech_ez15tt_02.webp",
      "target": "",
      "status": "no_match",
      "reason": "no_match"
    },
    {
      "source": "tapetech_ez15tt_03.webp",
      "target": "",
      "status": "no_match",
      "reason": "no_match"
    },
    {
      "source": "tapetech_ez15tt_04.webp",
      "target": "",
      "status": "no_match",
      "reason": "no_match"
    },
    {
      "source": "tapetech_ez15tt_05.webp",
      "target": "",
      "status": "no_match",
      "reason": "no_match"
    },
    {
      "source": "tapetech_ez15tt_06.webp",
      "target": "",
      "status": "no_match",
      "reason": "no_match"
    },
    {
      "source": "tapetech_ez15tt_07.webp",
      "target": "",
      "status": "no_match",
      "reason": "no_match"
    },
    {
      "source": "tapetech_ez15tt_08.webp",
      "target": "",
      "status": "no_match",
      "reason": "no_match"
    },
    {
      "source": "tapetech_ez15tt_09.webp",
      "target": "",
      "status": "no_match",
      "reason": "no_match"
    },
    {
      "source": "tapetech_ez15tt_10.webp",
      "target": "",
      "status": "no_match",
      "reason": "no_match"
    },
    {
      "source": "tapetech_ez15tt_11.webp",
      "target": "",
      "status": "no_match",
      "reason": "no_match"
    },
    {
      "source": "tapetech_fhtt_07.webp",
      "target": "",
      "status": "no_match",
      "reason": "no_match"
    },
    {
      "source": "tapetech_fhtt_08.webp",
      "target": "",
      "status": "no_match",
      "reason": "no_match"
    },
    {
      "source": "tapetech_fhtt_09.webp",
      "target": "",
      "status": "no_match",
      "reason": "no_match"
    },
    {
      "source": "tapetech_hwk001_ps_01.webp",
      "target": "",
      "status": "no_match",
      "reason": "no_match"
    },
    {
      "source": "tapetech_hwk001_ps_02.webp",
      "target": "",
      "status": "no_match",
      "reason": "no_match"
    },
    {
      "source": "tapetech_hwk001ps_01.webp",
      "target": "",
      "status": "no_match",
      "reason": "no_match"
    },
    {
      "source": "tapetech_hwk002_blk_01.webp",
      "target": "",
      "status": "no_match",
      "reason": "no_match"
    },
    {
      "source": "tapetech_hwk002_blk_02.webp",
      "target": "",
      "status": "no_match",
      "reason": "no_match"
    },
    {
      "source": "tapetech_jct01tt_01.webp",
      "target": "",
      "status": "no_match",
      "reason": "no_match"
    },
    {
      "source": "tapetech_jct01tt_02.webp",
      "target": "",
      "status": "no_match",
      "reason": "no_match"
    },
    {
      "source": "tapetech_jct01tt_03.webp",
      "target": "",
      "status": "no_match",
      "reason": "no_match"
    },
    {
      "source": "tapetech_jct01tt_04.webp",
      "target": "",
      "status": "no_match",
      "reason": "no_match"
    },
    {
      "source": "tapetech_jct01tt_05.webp",
      "target": "",
      "status": "no_match",
      "reason": "no_match"
    },
    {
      "source": "tapetech_jk01sstt_01.webp",
      "target": "",
      "status": "no_match",
      "reason": "no_match"
    },
    {
      "source": "tapetech_jk01sstt_02.webp",
      "target": "",
      "status": "no_match",
      "reason": "no_match"
    },
    {
      "source": "tapetech_jk02sstt_01.webp",
      "target": "",
      "status": "no_match",
      "reason": "no_match"
    },
    {
      "source": "tapetech_jk02sstt_02.webp",
      "target": "",
      "status": "no_match",
      "reason": "no_match"
    },
    {
      "source": "tapetech_jk03sstt_01.webp",
      "target": "",
      "status": "no_match",
      "reason": "no_match"
    },
    {
      "source": "tapetech_jk03sstt_02.webp",
      "target": "",
      "status": "no_match",
      "reason": "no_match"
    },
    {
      "source": "tapetech_jk03sstt_03.webp",
      "target": "",
      "status": "no_match",
      "reason": "no_match"
    },
    {
      "source": "tapetech_jk03sstt_04.webp",
      "target": "",
      "status": "no_match",
      "reason": "no_match"
    },
    {
      "source": "tapetech_jk03sstt_05.webp",
      "target": "",
      "status": "no_match",
      "reason": "no_match"
    },
    {
      "source": "tapetech_jk03sstt_06.webp",
      "target": "",
      "status": "no_match",
      "reason": "no_match"
    },
    {
      "source": "tapetech_jk03sstt_07.webp",
      "target": "",
      "status": "no_match",
      "reason": "no_match"
    },
    {
      "source": "tapetech_jk03sstt_08.webp",
      "target": "",
      "status": "no_match",
      "reason": "no_match"
    },
    {
      "source": "tapetech_jk03sstt_09.webp",
      "target": "",
      "status": "no_match",
      "reason": "no_match"
    },
    {
      "source": "tapetech_jk03sstt_10.webp",
      "target": "",
      "status": "no_match",
      "reason": "no_match"
    },
    {
      "source": "tapetech_jk04cstt_01.webp",
      "target": "",
      "status": "no_match",
      "reason": "no_match"
    },
    {
      "source": "tapetech_jk04cstt_02.webp",
      "target": "",
      "status": "no_match",
      "reason": "no_match"
    },
    {
      "source": "tapetech_jk04sstt_01.webp",
      "target": "",
      "status": "no_match",
      "reason": "no_match"
    },
    {
      "source": "tapetech_jk04sstt_02.webp",
      "target": "",
      "status": "no_match",
      "reason": "no_match"
    },
    {
      "source": "tapetech_jk05sstt_01.webp",
      "target": "",
      "status": "no_match",
      "reason": "no_match"
    },
    {
      "source": "tapetech_jk05sstt_02.webp",
      "target": "",
      "status": "no_match",
      "reason": "no_match"
    },
    {
      "source": "tapetech_jk06cstt_01.webp",
      "target": "",
      "status": "no_match",
      "reason": "no_match"
    },
    {
      "source": "tapetech_jk06cstt_02.webp",
      "target": "",
      "status": "no_match",
      "reason": "no_match"
    },
    {
      "source": "tapetech_jk06sstt_01.webp",
      "target": "",
      "status": "no_match",
      "reason": "no_match"
    },
    {
      "source": "tapetech_jk06sstt_02.webp",
      "target": "",
      "status": "no_match",
      "reason": "no_match"
    },
    {
      "source": "tapetech_js01_01.webp",
      "target": "",
      "status": "no_match",
      "reason": "no_match"
    },
    {
      "source": "tapetech_js01_02.webp",
      "target": "",
      "status": "no_match",
      "reason": "no_match"
    },
    {
      "source": "tapetech_js01_03.webp",
      "target": "",
      "status": "no_match",
      "reason": "no_match"
    },
    {
      "source": "tapetech_mp12sstt_01.webp",
      "target": "",
      "status": "no_match",
      "reason": "no_match"
    },
    {
      "source": "tapetech_mp12tt_01.webp",
      "target": "",
      "status": "no_match",
      "reason": "no_match"
    },
    {
      "source": "tapetech_mp12tt_02.webp",
      "target": "",
      "status": "no_match",
      "reason": "no_match"
    },
    {
      "source": "tapetech_mp12tt_03.webp",
      "target": "",
      "status": "no_match",
      "reason": "no_match"
    },
    {
      "source": "tapetech_mp14sstt_01.webp",
      "target": "",
      "status": "no_match",
      "reason": "no_match"
    },
    {
      "source": "tapetech_mp14tt_01.webp",
      "target": "",
      "status": "no_match",
      "reason": "no_match"
    },
    {
      "source": "tapetech_ns02tt_02.webp",
      "target": "",
      "status": "no_match",
      "reason": "no_match"
    },
    {
      "source": "tapetech_ns02tt_03.webp",
      "target": "",
      "status": "no_match",
      "reason": "no_match"
    },
    {
      "source": "tapetech_ns02tt_04.webp",
      "target": "",
      "status": "no_match",
      "reason": "no_match"
    },
    {
      "source": "tapetech_ns02tt_05.webp",
      "target": "",
      "status": "no_match",
      "reason": "no_match"
    },
    {
      "source": "tapetech_ns03tt_02.webp",
      "target": "",
      "status": "no_match",
      "reason": "no_match"
    },
    {
      "source": "tapetech_ns03tt_03.webp",
      "target": "",
      "status": "no_match",
      "reason": "no_match"
    },
    {
      "source": "tapetech_ns03tt_04.webp",
      "target": "",
      "status": "no_match",
      "reason": "no_match"
    },
    {
      "source": "tapetech_pahc07_02.webp",
      "target": "",
      "status": "no_match",
      "reason": "no_match"
    },
    {
      "source": "tapetech_pahc07_03.webp",
      "target": "",
      "status": "no_match",
      "reason": "no_match"
    },
    {
      "source": "tapetech_pahc07_04.webp",
      "target": "",
      "status": "no_match",
      "reason": "no_match"
    },
    {
      "source": "tapetech_pahc07_05.webp",
      "target": "",
      "status": "no_match",
      "reason": "no_match"
    },
    {
      "source": "tapetech_pahc07_06.webp",
      "target": "",
      "status": "no_match",
      "reason": "no_match"
    },
    {
      "source": "tapetech_pahc07_07.webp",
      "target": "",
      "status": "no_match",
      "reason": "no_match"
    },
    {
      "source": "tapetech_pahc10_02.webp",
      "target": "",
      "status": "no_match",
      "reason": "no_match"
    },
    {
      "source": "tapetech_pahc10_03.webp",
      "target": "",
      "status": "no_match",
      "reason": "no_match"
    },
    {
      "source": "tapetech_pahc10_04.webp",
      "target": "",
      "status": "no_match",
      "reason": "no_match"
    },
    {
      "source": "tapetech_pahc10_05.webp",
      "target": "",
      "status": "no_match",
      "reason": "no_match"
    },
    {
      "source": "tapetech_pahc10_06.webp",
      "target": "",
      "status": "no_match",
      "reason": "no_match"
    },
    {
      "source": "tapetech_pahc10_07.webp",
      "target": "",
      "status": "no_match",
      "reason": "no_match"
    },
    {
      "source": "tapetech_pahc10_08.webp",
      "target": "",
      "status": "no_match",
      "reason": "no_match"
    },
    {
      "source": "tapetech_pahc12_02.webp",
      "target": "",
      "status": "no_match",
      "reason": "no_match"
    },
    {
      "source": "tapetech_pahc12_03.webp",
      "target": "",
      "status": "no_match",
      "reason": "no_match"
    },
    {
      "source": "tapetech_pahc12_04.webp",
      "target": "",
      "status": "no_match",
      "reason": "no_match"
    },
    {
      "source": "tapetech_pahc12_05.webp",
      "target": "",
      "status": "no_match",
      "reason": "no_match"
    },
    {
      "source": "tapetech_pahc12_06.webp",
      "target": "",
      "status": "no_match",
      "reason": "no_match"
    },
    {
      "source": "tapetech_pahc12_07.webp",
      "target": "",
      "status": "no_match",
      "reason": "no_match"
    },
    {
      "source": "tapetech_pfk07tt_01.webp",
      "target": "",
      "status": "no_match",
      "reason": "no_match"
    },
    {
      "source": "tapetech_pfk07tt_02.webp",
      "target": "",
      "status": "no_match",
      "reason": "no_match"
    },
    {
      "source": "tapetech_pfk07tt_03.webp",
      "target": "",
      "status": "no_match",
      "reason": "no_match"
    },
    {
      "source": "tapetech_pfk07tt_04.webp",
      "target": "",
      "status": "no_match",
      "reason": "no_match"
    },
    {
      "source": "tapetech_pfk12tt_01.webp",
      "target": "",
      "status": "no_match",
      "reason": "no_match"
    },
    {
      "source": "tapetech_pfk12tt_02.webp",
      "target": "",
      "status": "no_match",
      "reason": "no_match"
    },
    {
      "source": "tapetech_pfk14tt_01.webp",
      "target": "",
      "status": "no_match",
      "reason": "no_match"
    },
    {
      "source": "tapetech_pfk14tt_02.webp",
      "target": "",
      "status": "no_match",
      "reason": "no_match"
    },
    {
      "source": "tapetech_pfk18tt_01.webp",
      "target": "",
      "status": "no_match",
      "reason": "no_match"
    },
    {
      "source": "tapetech_pfk18tt_02.webp",
      "target": "",
      "status": "no_match",
      "reason": "no_match"
    },
    {
      "source": "tapetech_pfk24tt_01.webp",
      "target": "",
      "status": "no_match",
      "reason": "no_match"
    },
    {
      "source": "tapetech_pfk24tt_02.webp",
      "target": "",
      "status": "no_match",
      "reason": "no_match"
    },
    {
      "source": "tapetech_pfk32tt_01.webp",
      "target": "",
      "status": "no_match",
      "reason": "no_match"
    },
    {
      "source": "tapetech_pfk32tt_02.webp",
      "target": "",
      "status": "no_match",
      "reason": "no_match"
    },
    {
      "source": "tapetech_pfk40tt_01.webp",
      "target": "",
      "status": "no_match",
      "reason": "no_match"
    },
    {
      "source": "tapetech_pfk40tt_02.webp",
      "target": "",
      "status": "no_match",
      "reason": "no_match"
    },
    {
      "source": "tapetech_pfk48tt_01.webp",
      "target": "",
      "status": "no_match",
      "reason": "no_match"
    },
    {
      "source": "tapetech_pfk48tt_02.webp",
      "target": "",
      "status": "no_match",
      "reason": "no_match"
    },
    {
      "source": "tapetech_pfkhatt_01.webp",
      "target": "",
      "status": "no_match",
      "reason": "no_match"
    },
    {
      "source": "tapetech_pfkhatt_02.webp",
      "target": "",
      "status": "no_match",
      "reason": "no_match"
    },
    {
      "source": "tapetech_pfkhatt_03.webp",
      "target": "",
      "status": "no_match",
      "reason": "no_match"
    },
    {
      "source": "tapetech_pfkhatt_04.webp",
      "target": "",
      "status": "no_match",
      "reason": "no_match"
    },
    {
      "source": "tapetech_pfkhatt_05.webp",
      "target": "",
      "status": "no_match",
      "reason": "no_match"
    },
    {
      "source": "tapetech_pfkhatt_06.webp",
      "target": "",
      "status": "no_match",
      "reason": "no_match"
    },
    {
      "source": "tapetech_pfkhatt_07.webp",
      "target": "",
      "status": "no_match",
      "reason": "no_match"
    },
    {
      "source": "tapetech_pfkhatt_08.webp",
      "target": "",
      "status": "no_match",
      "reason": "no_match"
    },
    {
      "source": "tapetech_pk35cstt_01.webp",
      "target": "",
      "status": "no_match",
      "reason": "no_match"
    },
    {
      "source": "tapetech_pk35cstt_02.webp",
      "target": "",
      "status": "no_match",
      "reason": "no_match"
    },
    {
      "source": "tapetech_pk35cstt_03.webp",
      "target": "",
      "status": "no_match",
      "reason": "no_match"
    },
    {
      "source": "tapetech_pk35cstt_04.webp",
      "target": "",
      "status": "no_match",
      "reason": "no_match"
    },
    {
      "source": "tapetech_pk35cstt_05.webp",
      "target": "",
      "status": "no_match",
      "reason": "no_match"
    },
    {
      "source": "tapetech_pmp001_01.webp",
      "target": "",
      "status": "no_match",
      "reason": "no_match"
    },
    {
      "source": "tapetech_pmp001_02.webp",
      "target": "",
      "status": "no_match",
      "reason": "no_match"
    },
    {
      "source": "tapetech_tt_basic_full_set_01.webp",
      "target": "",
      "status": "no_match",
      "reason": "no_match"
    },
    {
      "source": "tapetech_tt_basic_jumbo_set_01.webp",
      "target": "",
      "status": "no_match",
      "reason": "no_match"
    },
    {
      "source": "tapetech_tt_combo_corner_flusher_01.webp",
      "target": "",
      "status": "no_match",
      "reason": "no_match"
    },
    {
      "source": "tapetech_tt_compound_roller_with_frame_01.webp",
      "target": "",
      "status": "no_match",
      "reason": "no_match"
    },
    {
      "source": "tapetech_tt_corner_applicator_with_fhtt_handle_01.webp",
      "target": "",
      "status": "no_match",
      "reason": "no_match"
    },
    {
      "source": "tapetech_tt_easyclean_nail_spotter_with_fhtt_handle_01.webp",
      "target": "",
      "status": "no_match",
      "reason": "no_match"
    },
    {
      "source": "tapetech_tt_stainless_steel_mud_pan_01.webp",
      "target": "",
      "status": "no_match",
      "reason": "no_match"
    },
    {
      "source": "tapetech_ttbbs_02.webp",
      "target": "",
      "status": "no_match",
      "reason": "no_match"
    },
    {
      "source": "tapetech_ttpps_02.webp",
      "target": "",
      "status": "no_match",
      "reason": "no_match"
    },
    {
      "source": "tapetech_ttpps_03.webp",
      "target": "",
      "status": "no_match",
      "reason": "no_match"
    },
    {
      "source": "tapetech_ttpps_04.webp",
      "target": "",
      "status": "no_match",
      "reason": "no_match"
    },
    {
      "source": "tapetech_ttpps_05.webp",
      "target": "",
      "status": "no_match",
      "reason": "no_match"
    },
    {
      "source": "tapetech_ttpps_06.webp",
      "target": "",
      "status": "no_match",
      "reason": "no_match"
    },
    {
      "source": "tapetech_ttpps_07.webp",
      "target": "",
      "status": "no_match",
      "reason": "no_match"
    },
    {
      "source": "tapetech_ttppsef_02.webp",
      "target": "",
      "status": "no_match",
      "reason": "no_match"
    },
    {
      "source": "tapetech_ttppsef_03.webp",
      "target": "",
      "status": "no_match",
      "reason": "no_match"
    },
    {
      "source": "tapetech_ttppsef_04.webp",
      "target": "",
      "status": "no_match",
      "reason": "no_match"
    },
    {
      "source": "tapetech_ttppsef_05.webp",
      "target": "",
      "status": "no_match",
      "reason": "no_match"
    },
    {
      "source": "tapetech_ttppsef_06.webp",
      "target": "",
      "status": "no_match",
      "reason": "no_match"
    },
    {
      "source": "tapetech_ttpss_02.webp",
      "target": "",
      "status": "no_match",
      "reason": "no_match"
    },
    {
      "source": "tapetech_ttpss_04.webp",
      "target": "",
      "status": "no_match",
      "reason": "no_match"
    },
    {
      "source": "tapetech_vabs050_01.webp",
      "target": "",
      "status": "no_match",
      "reason": "no_match"
    },
    {
      "source": "tapetech_vabs130_01.webp",
      "target": "",
      "status": "no_match",
      "reason": "no_match"
    },
    {
      "source": "tapetech_vex11075_01.webp",
      "target": "",
      "status": "no_match",
      "reason": "no_match"
    },
    {
      "source": "tapetech_vex4030_01.webp",
      "target": "",
      "status": "no_match",
      "reason": "no_match"
    },
    {
      "source": "tapetech_vex8025_01.webp",
      "target": "",
      "status": "no_match",
      "reason": "no_match"
    },
    {
      "source": "tapetech_vex8060_01.webp",
      "target": "",
      "status": "no_match",
      "reason": "no_match"
    },
    {
      "source": "tapetech_vin11075_01.webp",
      "target": "",
      "status": "no_match",
      "reason": "no_match"
    },
    {
      "source": "tapetech_vin4030_01.webp",
      "target": "",
      "status": "no_match",
      "reason": "no_match"
    },
    {
      "source": "tapetech_vin8060_01.webp",
      "target": "",
      "status": "no_match",
      "reason": "no_match"
    },
    {
      "source": "tapetech_xhtt_08.webp",
      "target": "",
      "status": "no_match",
      "reason": "no_match"
    },
    {
      "source": "tapetech_xhtt_09.webp",
      "target": "",
      "status": "no_match",
      "reason": "no_match"
    },
    {
      "source": "tapetech_xhtt_10.webp",
      "target": "",
      "status": "no_match",
      "reason": "no_match"
    }
  ]
}