{
  "total_rows": 1654,
  "variations_without_parent_count": 0,
  "variations_without_parent_sample": [],
  "variations_parents_missing_or_not_variable_count": 0,
  "variations_parents_missing_or_not_variable_sample": [],
  "variable_parents_with_zero_children_count": 0,
  "variable_parents_with_zero_children_sample": [],
  "parent_child_counts_sample": {
    "AH-AD": 3,
    "EZFB-AD": 3,
    "PAFB-AD": 3,
    "COL-FBB": 4,
    "COL-FBBA": 3,
    "COL-FFB": 6,
    "COL-FFBA": 4,
    "COL-ITFB": 3,
    "COL-AH": 4,
    "COL-CSF": 3,
    "COL-DF": 3,
    "COL-SF": 3,
    "COL-NS": 2,
    "COL-BBH": 5,
    "COL-BH": 5,
    "COL-CFB": 2,
    "COL-AHBLADE": 4,
    "COL-AHSPRING": 4,
    "COL-AHRBK": 4,
    "COL-CMPX6": 2,
    "COL-CLT": 4,
    "COL-CMT": 4,
    "COL-CTK": 4,
    "COL-GN": 2,
    "COL-SB2": 6,
    "COL-SSB": 9,
    "COL-TSB": 7,
    "PT-FB": 4,
    "PT-NS": 2,
    "PT-CF": 3,
    "PT-BH": 3,
    "PT-CT": 3,
    "FBH-TT": 4,
    "EFBH-TT": 4,
    "CA-TT": 2,
    "CFBOX-TT": 3,
    "CAVH-TT": 4,
    "CROLL-TT": 3,
    "CT-TT": 3,
    "MAXXBOX-TT": 6,
    "EZFB-TT": 3,
    "JKSS-TT": 6,
    "NS-TT": 2,
    "PFB-TT": 8,
    "PFK-TT": 8,
    "QB-QSX": 2,
    "TKBS-TT": 4,
    "TKSS-TT": 4
  }
}